drf_simple_auth/__init__.py
drf_simple_auth/admin.py
drf_simple_auth/api.py
drf_simple_auth/api_exceptions.py
drf_simple_auth/apps.py
drf_simple_auth/auth.py
drf_simple_auth/models.py
drf_simple_auth/tests.py
drf_simple_auth/urls.py
drf_simple_auth/migrations/0001_initial.py
drf_simple_auth/migrations/0002_auto_20170802_2042.py
drf_simple_auth/migrations/0003_auto_20170802_2042.py
drf_simple_auth/migrations/__init__.py
drf_simple_auth-0.0.4.dist-info/DESCRIPTION.rst
drf_simple_auth-0.0.4.dist-info/METADATA
drf_simple_auth-0.0.4.dist-info/RECORD
drf_simple_auth-0.0.4.dist-info/WHEEL
drf_simple_auth-0.0.4.dist-info/metadata.json
drf_simple_auth-0.0.4.dist-info/pbr.json
drf_simple_auth-0.0.4.dist-info/top_level.txt
