Metadata-Version: 2.0
Name: drf-simple-auth
Version: 0.0.4
Summary: Simple login/signup APIs using Django Rest Framework.
Home-page: https://github.com/nickromano/drf-simple-auth
Author: Nick Romano
Author-email: nick.r.romano@gmail.com
License: UNKNOWN
Platform: UNKNOWN
Classifier: Framework :: Django
Classifier: Intended Audience :: Developers
Classifier: License :: OSI Approved :: MIT License
Classifier: Operating System :: OS Independent
Classifier: Programming Language :: Python
Classifier: Programming Language :: Python :: 2
Classifier: Programming Language :: Python :: 2.7
Classifier: Programming Language :: Python :: 3
Classifier: Programming Language :: Python :: 3.5
Requires-Dist: Django (>=1.10)
Requires-Dist: djangorestframework (>=3.6.3)
